optikon.py
optikon-0.4.0.dist-info/licenses/LICENSE
optikon-0.4.0.dist-info/METADATA
optikon-0.4.0.dist-info/WHEEL
optikon-0.4.0.dist-info/top_level.txt
optikon-0.4.0.dist-info/RECORD
