Metadata-Version: 2.4
Name: optikon
Version: 0.4.0
Summary: Optimisation of propositional conjunctions about numerical data
Author-email: Mario Boley <mario.boley@gmail.com>
License: MIT License
License-File: LICENSE
Requires-Dist: numpy==2.2.*,>=2.2.4
Requires-Dist: numba==0.61.*,>=0.61.2
Dynamic: license-file
